normalise/__init__.py
normalise/class_ALPHA.py
normalise/class_NUMB.py
normalise/command_line.py
normalise/detect.py
normalise/expand_EXPN.py
normalise/expand_HTAG.py
normalise/expand_NUMB.py
normalise/expand_all.py
normalise/normalisation.py
normalise/spellcheck.py
normalise/spelling.py
normalise/splitter.py
normalise/tag_MISC.py
normalise/tagger.py
normalise/data/NSW_dict.pickle
normalise/data/__init__.py
normalise/data/abbrev_dict.pickle
normalise/data/abbrev_dict.py
normalise/data/clf_ALPHA.pickle
normalise/data/clf_NUMB.pickle
normalise/data/contraction_list.py
normalise/data/element_dict.py
normalise/data/fake_data.pickle
normalise/data/measurements.py
normalise/data/names.pickle
normalise/data/pos_dicts.pickle
normalise/data/pos_tag_dict.py
normalise/data/sig_dict.pickle
normalise/data/tech_words.py
normalise/data/timezones.py
normalise/data/word_tokenized.pickle
normalise/data/word_tokenized_lowered.pickle
normalise/data/wordlist.pickle
normalise-0.1.8.dist-info/LICENSE.txt
normalise-0.1.8.dist-info/METADATA
normalise-0.1.8.dist-info/WHEEL
normalise-0.1.8.dist-info/entry_points.txt
normalise-0.1.8.dist-info/top_level.txt
normalise-0.1.8.dist-info/RECORD
